simpleelasticlogging/__init__.py
simpleelasticlogging/simpleelasticlogging.py
simpleelasticlogging-0.1.1.dist-info/LICENSE.md
simpleelasticlogging-0.1.1.dist-info/METADATA
simpleelasticlogging-0.1.1.dist-info/WHEEL
simpleelasticlogging-0.1.1.dist-info/top_level.txt
simpleelasticlogging-0.1.1.dist-info/RECORD
