Metadata-Version: 2.1
Name: simpleelasticlogging
Version: 0.1.1
Summary: A logger using Elasticsearch in the background with a focus on simplicity.
Home-page: https://github.com/JustinGuese/pip-simple-elasticsearch-logging
Author: Justin Guese
Author-email: guese.justin@gmail.com
License: UNKNOWN
Platform: UNKNOWN
Classifier: Programming Language :: Python :: 3
Classifier: License :: OSI Approved :: MIT License
Classifier: Operating System :: OS Independent
Requires-Dist: elasticsearch
